{
  "title": "GPM interactive demo",
  "sample": "beta-license-audited Western Europe (6 land provinces)",
  "geometry_tier": "scaffold-baseline",
  "note": "Politics are era overlays on modern scaffold geometry. Period shapes are reserved for M15+.",
  "scenarios": [
    {
      "id": "official-1444",
      "era": "1444",
      "label": "1444 \u00b7 EU-leaning",
      "politics_tier": "curated-politics",
      "start_date": "1444-11-11",
      "geojson": "official-1444.geojson",
      "legend": "official-1444.legend.json",
      "status": "live"
    },
    {
      "id": "official-1836",
      "era": "1836",
      "label": "1836 \u00b7 Victoria-leaning",
      "politics_tier": "curated-politics",
      "start_date": "1836-01-01",
      "geojson": "official-1836.geojson",
      "legend": "official-1836.legend.json",
      "status": "live"
    },
    {
      "id": "modern-baseline",
      "era": "modern",
      "label": "Modern baseline",
      "politics_tier": "scaffold-baseline",
      "start_date": "2020-01-01",
      "geojson": "modern-baseline.geojson",
      "legend": "modern-baseline.legend.json",
      "status": "live"
    }
  ],
  "live_layers": [
    {
      "id": "ownership",
      "label": "Owner choropleth",
      "desc": "Scenario owner colors from atlas export"
    },
    {
      "id": "assignment",
      "label": "Assignment source",
      "desc": "baseline \u00b7 country_rule \u00b7 region_rule \u00b7 province_override"
    },
    {
      "id": "adjacency",
      "label": "Adjacency graph",
      "desc": "Land / sea / port edges from sample graph"
    },
    {
      "id": "labels",
      "label": "Province labels",
      "desc": "Stable IDs + display names"
    },
    {
      "id": "inspector",
      "label": "Province inspector",
      "desc": "Owner, controller, cores, claims, lineage fields"
    }
  ],
  "future_slots": [
    {
      "id": "period-geometry",
      "label": "Period geometry",
      "milestone": "M15",
      "desc": "Era-aware province shapes for priority regions"
    },
    {
      "id": "boundary-hints",
      "label": "Historical boundary hints",
      "milestone": "M15",
      "desc": "Soft frontier bands without full redraw"
    },
    {
      "id": "multi-era-packs",
      "label": "Multi-era geometry packs",
      "milestone": "M16",
      "desc": "Paired geometry + politics with ID lineage maps"
    },
    {
      "id": "era-1936",
      "label": "Official 1936 scenario",
      "milestone": "M16+",
      "desc": "HOI-leaning curated politics program"
    },
    {
      "id": "culture-religion",
      "label": "Culture & religion paint",
      "milestone": "M17",
      "desc": "Atlas layers for explanation products"
    },
    {
      "id": "pmtiles",
      "label": "PMTiles / vector tiles",
      "milestone": "M16+",
      "desc": "Web-scale delivery beyond sample GeoJSON"
    },
    {
      "id": "curation-diff",
      "label": "Curation diffs & golden borders",
      "milestone": "M17",
      "desc": "Community contribution and acceptance tests"
    }
  ],
  "export_faces": [
    {
      "id": "pack",
      "command": "gpm export pack",
      "label": "Game template pack"
    },
    {
      "id": "atlas",
      "command": "gpm export atlas",
      "label": "Atlas / SaaS face"
    }
  ]
}
