{"areas":[],"components":["tc-burgundy-duchy","tc-burgundy-low-countries","tc-calais-core","tc-calais-fragment","tc-free-city-krakow","tc-jiaozhou-concession","tc-neutral-moresnet","tc-papal-avignon","tc-papal-rome","tc-san-marino","tc-vilnius-region"],"political_units":["pu-austria","pu-belgium","pu-burgundy-duchy","pu-burgundy-low-countries","pu-china","pu-duke-of-burgundy","pu-english-calais","pu-free-city-krakow","pu-german-empire","pu-jiaozhou-concession","pu-kingdom-england","pu-lithuania","pu-neutral-moresnet","pu-papal-states","pu-poland","pu-prussia","pu-russia","pu-san-marino","pu-vilnius-dispute"],"provinces":["prv-burgundy-duchy","prv-burgundy-low-countries","prv-free-city-krakow","prv-jiaozhou-concession","prv-neutral-moresnet","prv-pale-of-calais","prv-papal-avignon","prv-papal-rome","prv-san-marino","prv-vilnius-region"],"regions":[],"relationships":["sovereign","owner","controller","protector","co-administrator","occupier","mandate-authority","lessee","claimant"],"scenarios":["composite-burgundian-possessions-1444","condominium-neutral-moresnet-1836","detached-papal-avignon-1444","disputed-vilnius-region-1936","foreign-exclave-calais-1444","leased-concession-jiaozhou-1914","microstate-san-marino-1444","protected-free-city-krakow-1836"],"superregions":[]}
